pymnesia/__init__.py
pymnesia/api/__init__.py
pymnesia/api/command/__init__.py
pymnesia/api/entities/__init__.py
pymnesia/api/entities/base.py
pymnesia/api/entities/fields.py
pymnesia/api/unit_of_work/__init__.py
pymnesia/core/__init__.py
pymnesia/core/common/__init__.py
pymnesia/core/common/originator_interface.py
pymnesia/core/composition/__init__.py
pymnesia/core/entities/__init__.py
pymnesia/core/entities/base.py
pymnesia/core/entities/entity.py
pymnesia/core/entities/entity_cls_conf.py
pymnesia/core/entities/entity_cls_resolver_interface.py
pymnesia/core/entities/entity_resolver.py
pymnesia/core/entities/field.py
pymnesia/core/entities/meta.py
pymnesia/core/entities/registry/__init__.py
pymnesia/core/entities/registry/exceptions/__init__.py
pymnesia/core/entities/registry/exceptions/missing_primary_key.py
pymnesia/core/entities/registry/exceptions/missing_tablename.py
pymnesia/core/entities/registry/interface.py
pymnesia/core/entities/registry/registry.py
pymnesia/core/entities/relations.py
pymnesia/core/query/__init__.py
pymnesia/core/query/engine/__init__.py
pymnesia/core/query/engine/base.py
pymnesia/core/query/engine/meta.py
pymnesia/core/query/filter/__init__.py
pymnesia/core/query/filter/functions.py
pymnesia/core/query/filter/registry.py
pymnesia/core/query/filter/relations.py
pymnesia/core/query/functions/__init__.py
pymnesia/core/query/query.py
pymnesia/core/query/runner.py
pymnesia/core/transaction/__init__.py
pymnesia/core/transaction/transaction.py
pymnesia/core/unit_of_work/__init__.py
pymnesia/core/unit_of_work/memento/__init__.py
pymnesia/core/unit_of_work/memento/base.py
pymnesia/core/unit_of_work/memento/meta.py
pymnesia/core/unit_of_work/meta.py
pymnesia/core/unit_of_work/unit_of_work.py
pymnesia-1.0.1b1.dist-info/LICENSE
pymnesia-1.0.1b1.dist-info/METADATA
pymnesia-1.0.1b1.dist-info/WHEEL
pymnesia-1.0.1b1.dist-info/RECORD
