Metadata-Version: 2.1
Name: pymnesia
Version: 1.0.1b1
Summary: A (real) in memory database and ORM
License: MIT
Author: Harold Cohen
Author-email: me@harold-cohen.com
Requires-Python: >=3.10.6,<4.0.0
Classifier: Development Status :: 4 - Beta
Classifier: License :: OSI Approved :: MIT License
Classifier: Operating System :: OS Independent
Classifier: Programming Language :: Python :: 3
Classifier: Programming Language :: Python :: 3.11
Classifier: Programming Language :: Python :: 3.12
Classifier: Topic :: Software Development :: Testing
